cli/__init__.py
cli/main.py
cli/commands/__init__.py
cli/commands/base.py
cli/commands/chat.py
cli/commands/config.py
cli/commands/generate.py
cli/commands/interactive.py
cli/commands/models.py
cli/commands/server.py
cli/utils/__init__.py
cli/utils/logging.py
cli/utils/models.py
getllm/.env
getllm/SCRAPER.md
getllm/UnifiedModelsManager.py
getllm/__init__.py
getllm/__main__.py
getllm/api.py
getllm/app.py
getllm/cli.py
getllm/debug_ollama.com_library.html
getllm/hf_models.json
getllm/hf_test.json
getllm/huggingface_models.json
getllm/interactive_cli.py
getllm/logging_config.py
getllm/model_scraper_integration.py
getllm/model_scrapers.py
getllm/models.py
getllm/models_metadata.json
getllm/ollama_integration.py
getllm/ollama_models.json
getllm/scraper_demo.py
getllm/test_scrapers.py
getllm/test_scrapers_integration.py
getllm/__pycache__/__init__.cpython-310.pyc
getllm/__pycache__/__init__.cpython-312.pyc
getllm/__pycache__/__init__.cpython-313.pyc
getllm/__pycache__/__main__.cpython-312.pyc
getllm/__pycache__/__main__.cpython-313.pyc
getllm/__pycache__/api.cpython-312.pyc
getllm/__pycache__/cli.cpython-312.pyc
getllm/__pycache__/cli.cpython-313.pyc
getllm/__pycache__/interactive_cli.cpython-312.pyc
getllm/__pycache__/interactive_cli.cpython-313.pyc
getllm/__pycache__/ollama_integration.cpython-312.pyc
getllm/__pycache__/ollama_integration.cpython-313.pyc
getllm/__pycache__/test_scrapers.cpython-312.pyc
getllm/__pycache__/test_scrapers_integration.cpython-312.pyc
getllm/models/__init__.py
getllm/models/base.py
getllm/models/huggingface.py
getllm/models/interactive.py
getllm/models/metadata.py
getllm/models/ollama.py
getllm/models/utils.py
getllm/models/__pycache__/__init__.cpython-310.pyc
getllm/models/__pycache__/__init__.cpython-312.pyc
getllm/models/__pycache__/__init__.cpython-313.pyc
getllm/models/__pycache__/base.cpython-310.pyc
getllm/models/__pycache__/base.cpython-312.pyc
getllm/models/__pycache__/base.cpython-313.pyc
getllm-0.1.71.dist-info/licenses/LICENSE
getllm-0.1.71.dist-info/METADATA
getllm-0.1.71.dist-info/WHEEL
getllm-0.1.71.dist-info/top_level.txt
getllm-0.1.71.dist-info/RECORD
