Metadata-Version: 2.4
Name: getllm
Version: 0.1.71
Summary: Python LLM operations service for the DevLama ecosystem
Home-page: https://github.com/py-lama/devlama
Author: Tom Sapletta
Author-email: Tom Sapletta <info@softreck.dev>
License: Apache-2.0
Project-URL: Homepage, https://github.com/py-lama/getllm
Project-URL: Documentation, https://py-lama.github.io/getllm/
Project-URL: Repository, https://github.com/py-lama/getllm
Project-URL: Changelog, https://github.com/py-lama/getllm/blob/main/CHANGELOG.md
Project-URL: Tracker, https://github.com/py-lama/getllm/issues
Project-URL: Discussions, https://github.com/py-lama/getllm/discussions
Project-URL: Download, https://pypi.org/project/getllm/
Classifier: Development Status :: 3 - Alpha
Classifier: Intended Audience :: Developers
Classifier: License :: OSI Approved :: Apache Software License
Classifier: Programming Language :: Python :: 3
Classifier: Programming Language :: Python :: 3.8
Classifier: Programming Language :: Python :: 3.9
Classifier: Programming Language :: Python :: 3.10
Classifier: Programming Language :: Python :: 3.11
Classifier: Programming Language :: Python :: 3.12
Classifier: Topic :: Software Development :: Libraries :: Python Modules
Requires-Python: >=3.8,<4.0
License-File: LICENSE
Requires-Dist: requests<3.0.0,>=2.31.0
Requires-Dist: bs4<0.0.2,>=0.0.1
Requires-Dist: beautifulsoup4<5.0.0,>=4.12.2
Requires-Dist: python-dotenv<2.0.0,>=1.0.0
Requires-Dist: questionary<3.0.0,>=2.0.1
Requires-Dist: appdirs<2.0.0,>=1.4.4
Requires-Dist: rich<15.0.0,>=14.0.0
Dynamic: author
Dynamic: home-page
Dynamic: license-file
Dynamic: requires-python
